S3IncrementalProcessor.py
S3IncrementalProcessor-0.1.2.dist-info/METADATA
S3IncrementalProcessor-0.1.2.dist-info/WHEEL
S3IncrementalProcessor-0.1.2.dist-info/top_level.txt
S3IncrementalProcessor-0.1.2.dist-info/RECORD
